botastico/__init__.py
botastico/botastico.py
botastico/langchain.py
botastico-0.1.7.dist-info/LICENSE
botastico-0.1.7.dist-info/METADATA
botastico-0.1.7.dist-info/WHEEL
botastico-0.1.7.dist-info/RECORD
