Metadata-Version: 2.1
Name: botastico
Version: 0.1.7
Summary: Python SDK for using the botasti.co chat API
Home-page: https://github.com/botastico/botastico-python
Author: Andres Kull
Requires-Python: >=3.11,<4.0
Classifier: Programming Language :: Python :: 3
Classifier: Programming Language :: Python :: 3.11
Requires-Dist: aiohttp (>=3.8.4,<4.0.0)
Requires-Dist: asyncio (>=3.4.3,<4.0.0)
Requires-Dist: langchain (>=0.0.231,<0.0.232)
Requires-Dist: python-semantic-release (>=7.34.6,<8.0.0)
